base.py
helper.py
waste_simulation.py
waste_simulation-0.0.3.dist-info/METADATA
waste_simulation-0.0.3.dist-info/WHEEL
waste_simulation-0.0.3.dist-info/top_level.txt
waste_simulation-0.0.3.dist-info/RECORD
