Metadata-Version: 2.1
Name: waste-simulation
Version: 0.0.3
Summary: UNKNOWN
Home-page: UNKNOWN
Author: Justin Rush
Author-email: jandrewrush@gmail.com
License: UNKNOWN
Platform: UNKNOWN
Requires-Dist: pandas
